dvadmin_sms/__init__.py
dvadmin_sms/apps.py
dvadmin_sms/models.py
dvadmin_sms/settings.py
dvadmin_sms/urls.py
dvadmin_sms/utils.py
dvadmin_sms/wechat.py
dvadmin_sms/api/__init__.py
dvadmin_sms/api/alibabacloud.py
dvadmin_sms/api/tencent_cloud.py
dvadmin_sms/fixtures/__init__.py
dvadmin_sms/fixtures/init_dictionary.json
dvadmin_sms/fixtures/init_menu.json
dvadmin_sms/fixtures/init_systemconfig.json
dvadmin_sms/fixtures/initialize.py
dvadmin_sms/migrations/__init__.py
dvadmin_sms/views/__init__.py
dvadmin_sms/views/send_sms.py
dvadmin_sms-1.0.7.dist-info/LICENSE
dvadmin_sms-1.0.7.dist-info/METADATA
dvadmin_sms-1.0.7.dist-info/WHEEL
dvadmin_sms-1.0.7.dist-info/top_level.txt
dvadmin_sms-1.0.7.dist-info/RECORD
