Metadata-Version: 2.1
Name: dvadmin-sms
Version: 1.0.7
Summary: 一款适用于django-vue-admin基于阿里云、腾讯云、华为云等官方短信服务开发的短信发送插件，快速整合各端的短信服务插件。
Home-page: https://gitee.com/huge-dream/dvadmin-sms
Author: DVAdmin
Author-email: liqiang@django-vue-admin.com
Classifier: Programming Language :: Python :: 3
Classifier: License :: OSI Approved :: MIT License
Classifier: Operating System :: OS Independent
Requires-Python: >=3.7, <4
License-File: LICENSE
Requires-Dist: alibabacloud-dysmsapi20170525 (>=2.0.23)
Requires-Dist: tencentcloud-sdk-python (>=3.0.911)
